Metadata-Version: 2.4
Name: segdan
Version: 0.1.6
Summary: AutoML framework for the construction of segmentation models.
Home-page: https://github.com/joortif/SegDAN
Author: Joaquin Ortiz de Murua Ferrero
Author-email: joortif@unirioja.es
Maintainer: Joaquin Ortiz de Murua Ferrero
Maintainer-email: joortif@unirioja.es
License: MIT license
Keywords: instance semantic segmentation pytorch huggingface embedding image analysis deep learning active learning computer vision
Classifier: Development Status :: 4 - Beta
Classifier: Programming Language :: Python :: 3.10
Classifier: Intended Audience :: Science/Research
Classifier: Intended Audience :: Developers
Classifier: Topic :: Scientific/Engineering :: Image Recognition
Classifier: Topic :: Scientific/Engineering :: Artificial Intelligence
Classifier: Operating System :: OS Independent
Requires-Python: >=3.9
License-File: LICENSE.txt
Requires-Dist: albumentations>=2.0.6
Requires-Dist: huggingface_hub>=0.26.2
Requires-Dist: imagedatasetanalyzer>=0.4.0
Requires-Dist: matplotlib>=3.8.4
Requires-Dist: numpy>=1.26.4
Requires-Dist: opencv_contrib_python>=4.9.0.80
Requires-Dist: opencv_python>=4.9.0.80
Requires-Dist: opencv_python_headless>=4.9.0.80
Requires-Dist: pandas>=2.2.3
Requires-Dist: Pillow>=11.0.0
Requires-Dist: plotly>=6.0.1
Requires-Dist: PyYAML>=6.0.2
Requires-Dist: Requests>=2.32.3
Requires-Dist: scikit_learn>=1.4.2
Requires-Dist: scikit_multilearn>=0.2.0
Requires-Dist: scikit-image>=0.22.0
Requires-Dist: scipy>=1.13.0
Requires-Dist: tensorflow>=2.18.0
Requires-Dist: tkinter_tooltip>=3.1.2
Requires-Dist: tqdm>=4.66.6
Requires-Dist: ultralytics>=8.3.28
Requires-Dist: kneed>=0.8.5
Requires-Dist: lpips>=0.1.4
Requires-Dist: piq>=0.8.0
Requires-Dist: transformers>=4.38.2
Requires-Dist: tf-keras
Dynamic: author
Dynamic: author-email
Dynamic: classifier
Dynamic: description
Dynamic: description-content-type
Dynamic: home-page
Dynamic: keywords
Dynamic: license
Dynamic: license-file
Dynamic: maintainer
Dynamic: maintainer-email
Dynamic: requires-dist
Dynamic: requires-python
Dynamic: summary
